LICENSE
MANIFEST.in
README.rst
setup.py
django_optin.egg-info/PKG-INFO
django_optin.egg-info/SOURCES.txt
django_optin.egg-info/dependency_links.txt
django_optin.egg-info/top_level.txt
optin/__init__.py
optin/admin.py
optin/apps.py
optin/config.py
optin/forms.py
optin/models.py
optin/tests.py
optin/urls.py
optin/utils.py
optin/views.py
optin/migrations/0001_initial.py
optin/migrations/__init__.py
optin/templates/optin/optin_form.html