Metadata-Version: 1.1
Name: django-optin
Version: 1.0.0
Summary: A simple Django app to manage User Preferences.
Home-page: https://github.com/HenryMehta/django-optin
Author: Henry Mehta
Author-email: hjsmehta@gmail.com
License: MIT License
Platform: UNKNOWN
Classifier: Environment :: Web Environment
Classifier: Framework :: Django
Classifier: Framework :: Django :: 1.11
Classifier: Intended Audience :: Developers
Classifier: License :: OSI Approved :: MIT License
Classifier: Operating System :: OS Independent
Classifier: Programming Language :: Python
Classifier: Programming Language :: Python :: 2.7
Classifier: Topic :: Internet :: WWW/HTTP
Classifier: Topic :: Internet :: WWW/HTTP :: Dynamic Content
